capturepy.py
capturepy-1.0.3.dist-info/LICENSE
capturepy-1.0.3.dist-info/METADATA
capturepy-1.0.3.dist-info/WHEEL
capturepy-1.0.3.dist-info/top_level.txt
capturepy-1.0.3.dist-info/RECORD
