Metadata-Version: 2.1
Name: capturepy
Version: 1.0.3
Summary: Capturepy captures the standard output and the standard error of functions, methods and any blocks of code. It is useful when testing, debugging and working with libraries. Find out more at https://github.com/GabrieleMaurina/capturepy.
Home-page: https://github.com/GabrieleMaurina/capturepy
Author: Gabriele Maurina
Author-email: gabrielemaurina95@gmail.com
License: MIT
Platform: UNKNOWN
Classifier: Programming Language :: Python :: 3
Classifier: License :: OSI Approved :: MIT License
Classifier: Operating System :: OS Independent
Requires-Python: >=3.8
